rwkv6_keras_operator/__init__.py
rwkv6_keras_operator/jax_rwkv_kernel.py
rwkv6_keras_operator/ops_rwkv_kernel.py
rwkv6_keras_operator/torch_rwkv_kernel.py
rwkv6_keras_operator/jax_kernel/gpu_ops.cpp
rwkv6_keras_operator/jax_kernel/kernel_helpers.h
rwkv6_keras_operator/jax_kernel/kernels.h
rwkv6_keras_operator/jax_kernel/pybind11_kernel_helpers.h
rwkv6_keras_operator/jax_kernel/rwkv_kernels.cu
rwkv6_keras_operator/torch_kernel/wkv6_cuda.cu
rwkv6_keras_operator/torch_kernel/wkv6_op.cpp
rwkv6_keras_operator-1.0.5.dist-info/METADATA
rwkv6_keras_operator-1.0.5.dist-info/WHEEL
rwkv6_keras_operator-1.0.5.dist-info/licenses/LICENSE
rwkv6_keras_operator-1.0.5.dist-info/RECORD
