Metadata-Version: 2.3
Name: rwkv6-keras-operator
Version: 1.0.5
Summary: A rwkv6 operator based on Keras3 which support JAX(CUDA)、Pytorch(CUDA)、Tensorflow(NATIVE).
Project-URL: Homepage, https://github.com/infiy-quine/RWKV6_Keras_Operator
Author-email: soyamilk <soyamilk1997@163.com>, pass-lin <qw_lin@qq.com>, szxy <szxysdt@outlook.com>, Beortust <Beortust@outlook.com>, itoos <2948395900@qq.com>, zoulion <zoulion@126.com>
License: MIT License
License-File: LICENSE
Classifier: License :: OSI Approved :: MIT License
Classifier: Operating System :: OS Independent
Classifier: Programming Language :: Python :: 3
Requires-Python: >=3.9
Requires-Dist: keras>=3.4
